manmade_mathinput/MathInput.py
manmade_mathinput/__init__.py
manmade_mathinput/_imports_.py
manmade_mathinput/manmade_mathinput.min.js
manmade_mathinput/manmade_mathinput.min.js.map
manmade_mathinput/metadata.json
manmade_mathinput/package-info.json
manmade_mathinput-0.0.3.dist-info/LICENSE
manmade_mathinput-0.0.3.dist-info/METADATA
manmade_mathinput-0.0.3.dist-info/WHEEL
manmade_mathinput-0.0.3.dist-info/top_level.txt
manmade_mathinput-0.0.3.dist-info/RECORD
