Metadata-Version: 2.1
Name: manmade_mathinput
Version: 0.0.3
Summary: Project Description
Author: Mads Kristensen <madskris@proton.me>
License: MIT
Classifier: Framework :: Dash
License-File: LICENSE
